chatq_helper/__init__.py
chatq_helper/exceptions.py
chatq_helper/mqtt.py
chatq_helper-0.0.4.dist-info/METADATA
chatq_helper-0.0.4.dist-info/WHEEL
chatq_helper-0.0.4.dist-info/top_level.txt
chatq_helper-0.0.4.dist-info/RECORD
