Metadata-Version: 2.1
Name: chatq-helper
Version: 0.0.4
Summary: chatq_helper
Home-page: https://github.com/ChatQSG/chatq-helping-hand
Author: ChatQ
Author-email: UNKNOWN
License: UNKNOWN
Platform: UNKNOWN
Requires-Dist: paho-mqtt (==1.3.1)
